asyncraft/__init__.py
asyncraft/broker.py
asyncraft/handler.py
asyncraft/message.py
asyncraft/pool.py
asyncraft/queues.py
asyncraft-0.0.3.dist-info/METADATA
asyncraft-0.0.3.dist-info/WHEEL
asyncraft-0.0.3.dist-info/licenses/LICENSE
asyncraft-0.0.3.dist-info/RECORD
