Metadata-Version: 2.3
Name: asyncraft
Version: 0.0.3
Summary: Simple message/event passing with asyncio and threading support.
Project-URL: Homepage, https://github.com/Morxos/asyncraft
Project-URL: Issues, https://github.com/Morxos/asyncraft/issues
Author-email: Kilian Müller <kilian@mueller.ai>
License-File: LICENSE
Classifier: License :: OSI Approved :: MIT License
Classifier: Operating System :: OS Independent
Classifier: Programming Language :: Python :: 3
Requires-Python: >=3.8
